alphatrion/__init__.py
alphatrion/consts.py
alphatrion/artifact/__init__.py
alphatrion/artifact/artifact.py
alphatrion/experiment/__init__.py
alphatrion/experiment/base.py
alphatrion/experiment/craft_exp.py
alphatrion/log/__init__.py
alphatrion/log/log.py
alphatrion/metadata/__init__.py
alphatrion/metadata/base.py
alphatrion/metadata/sql.py
alphatrion/metadata/sql_models.py
alphatrion/model/__init__.py
alphatrion/model/model.py
alphatrion/run/__init__.py
alphatrion/run/run.py
alphatrion/runtime/__init__.py
alphatrion/runtime/runtime.py
alphatrion/server/__init__.py
alphatrion/server/cmd/__init__.py
alphatrion/server/cmd/app.py
alphatrion/server/cmd/main.py
alphatrion/server/graphql/__init__.py
alphatrion/server/graphql/resolvers.py
alphatrion/server/graphql/runtime.py
alphatrion/server/graphql/schema.py
alphatrion/server/graphql/types.py
alphatrion/static/alphatrion.png
alphatrion/static/index.html
alphatrion/static/logo.png
alphatrion/static/assets/index-CZjEehIf.css
alphatrion/static/assets/index-DzgxcILT.js
alphatrion/tracing/__init__.py
alphatrion/tracing/tracing.py
alphatrion/trial/__init__.py
alphatrion/trial/trial.py
alphatrion/utils/__init__.py
alphatrion/utils/context.py
alphatrion/utils/time.py
alphatrion-0.1.0.dist-info/METADATA
alphatrion-0.1.0.dist-info/WHEEL
alphatrion-0.1.0.dist-info/entry_points.txt
alphatrion-0.1.0.dist-info/licenses/LICENSE
alphatrion-0.1.0.dist-info/RECORD
