Metadata-Version: 2.4
Name: alphatrion
Version: 0.1.0
Summary: ⚒️ AlphaTrion is an open-source framework to help build GenAI applications, including experiment tracking, adaptive model routing, prompt optimization and performance evaluation.
License: Apache-2.0
License-File: LICENSE
Requires-Python: >=3.12
Requires-Dist: alembic<2.0.0,>=1.17.1
Requires-Dist: fastapi>=0.121.2
Requires-Dist: openai<3.0.0,>=2.6.1
Requires-Dist: oras<0.3.0,>=0.2.38
Requires-Dist: pg8000>=1.31.5
Requires-Dist: psycopg2-binary<3.0.0,>=2.9.10
Requires-Dist: pydantic<3.0.0,>=2.11.7
Requires-Dist: python-dotenv<2.0.0,>=1.1.1
Requires-Dist: rich>=14.2.0
Requires-Dist: sqlalchemy<3.0.0,>=2.0.43
Requires-Dist: strawberry-graphql>=0.285.0
Requires-Dist: traceloop-sdk<1.0.0,>=0.47.5
Requires-Dist: uvicorn>=0.38.0
